LoraDroidClient/__init__.py
LoraDroidClient/client.py
LoraDroidClient/converter/__init__.py
LoraDroidClient/grpc_interface/__init__.py
LoraDroidClient/grpc_interface/bot_pb2.py
LoraDroidClient/grpc_interface/bot_pb2_grpc.py
LoraDroidClient-0.1.0.dist-info/METADATA
LoraDroidClient-0.1.0.dist-info/WHEEL
LoraDroidClient-0.1.0.dist-info/top_level.txt
LoraDroidClient-0.1.0.dist-info/RECORD
