Metadata-Version: 2.1
Name: LoraDroidClient
Version: 0.1.0
Summary: Python client for connecting to LORA Technologies' bot services.
Home-page: https://asklora.ai
Author: LORA Tech
Author-email: asklora@loratechai.com
License: UNKNOWN
Platform: UNKNOWN
Requires-Dist: grpcio (==1.43.0)
Requires-Dist: grpcio-tools (==1.43.0)
Requires-Dist: protobuf (==3.19.4)
Requires-Dist: setuptools (==58.0.4)
Requires-Dist: six (==1.16.0)
